[
    {
        "name": "Javascript",
        "icon": "/js_icon.png",
        "category": "frontend"
    },
    {
        "name": "Typescript",
        "icon": "/ts_icon.png",
        "category": "frontend"
    },
    {
        "name": "React JS",
        "icon": "/react_icon.png",
        "category": "frontend"
    },
    {
        "name": "Next.js",
        "icon": "/nextjs_icon.png",
        "category": "frontend"
    },
    {
        "name": "Vue.js",
        "icon": "/vuejs_icon.png",
        "category": "frontend"
    },
    {
        "name": "Alpine.js",
        "icon": "/alpinejs_icon.png",
        "category": "frontend"
    },
    {
        "name": "Livewirre",
        "icon": "/livewire_icon.png",
        "category": "frontend"
    },
    {
        "name": "Bootstrap 5",
        "icon": "/bootstrap_icon.png",
        "category": "frontend"
    },
    {
        "name": "Tailwind CSS",
        "icon": "/tailwind_icon.png",
        "category": "frontend"
    },
    {
        "name": "jQuery",
        "icon": "/jquery_icon.png",
        "category": "frontend"
    },
    {
        "name": "Node.js",
        "icon": "/nodejs_icon.png",
        "category": "backend"
    },
    {
        "name": "Bun.js",
        "icon": "/bunjs_icon.png",
        "category": "backend"
    },
    {
        "name": "NestJs",
        "icon": "/nestjs_icon.png",
        "category": "backend"
    },
    {
        "name": "Express.js",
        "icon": "/express_icon.png",
        "category": "backend"
    },
    {
        "name": "PHP",
        "icon": "/php_icon.png",
        "category": "backend"
    },
    {
        "name": "Laravel",
        "icon": "/laravel_icon.png",
        "category": "backend"
    },
    {
        "name": "Code Igniter",
        "icon": "/ci_icon.png",
        "category": "backend"
    },
    {
        "name": "Go (Golang)",
        "icon": "/go_icon.png",
        "category": "backend"
    },
    {
        "name": "Gin-Gonic",
        "icon": "/gin-gonic_icon.png",
        "category": "backend"
    },
    {
        "name": "RabbitMQ",
        "icon": "/rabbitMQ_icon.png",
        "category": "backend"
    },
    {
        "name": "MySQL",
        "icon": "/mysql_icon.png",
        "category": "database"
    },
    {
        "name": "PostgreSQL",
        "icon": "/postgresSQL_icon.png",
        "category": "database"
    },
    {
        "name": "MongoDB",
        "icon": "/mongoose_icon.png",
        "category": "database"
    },
    {
        "name": "Redis",
        "icon": "/redis_icon.png",
        "category": "database"
    },
    {
        "name": "Elastic Search",
        "icon": "/elasticSearch_icon.png",
        "category": "database"
    },
    {
        "name": "GORM",
        "icon": "/gorm_icon.png",
        "category": "database"
    },
    {
        "name": "Prisma ORM",
        "icon": "/prisma_icon.png",
        "category": "database"
    },
    {
        "name": "AWS",
        "icon": "/aws_icon.png",
        "category": "cloud"
    },
    {
        "name": "Google Cloud",
        "icon": "/gcp_icon.png",
        "category": "cloud"
    },
    {
        "name": "Firebase",
        "icon": "/firebase_icon.png",
        "category": "cloud"
    },
    {
        "name": "Sanity",
        "icon": "/sanity_icon.png",
        "category": "tools"
    },
    {
        "name": "Docker",
        "icon": "/docker_icon.png",
        "category": "tools"
    },
    {
        "name": "Git",
        "icon": "/git_icon.png",
        "category": "tools"
    }
]